{"0":false,"nav_menu_locations":{"header-menu-1":"[[term_id?taxonomy=nav_menu&slug=primary-menu]]","header-mobile-menu":"[[term_id?taxonomy=nav_menu&slug=mobile-menu]]"},"custom_css_post_id":-1,"custom_logo":"[[post_id?post_type=attachment&slug=logo-navy]]","header_main_bar_height":"120px","header_logo_width":"240px","blog_index_loop_mode":"grid","body_font_family":"google_fonts|Lato","body_font_size":"18px","body_line_height":"1.5","body_font_weight":"400","body_letter_spacing":"0.05em","h1_font_family":"google_fonts|Lato","h1_font_weight":"700","h1_font_size":"50px","h1_letter_spacing":"0.05em","h2_font_weight":"700","h2_font_size":"30px","h2_font_family":"google_fonts|Lato","h2_line_height":"1.3","h3_font_family":"google_fonts|Lato","h3_font_weight":"700","h3_line_height":"1.3","h4_font_family":"google_fonts|Lato","h4_font_weight":"700","h3_font_size":"26px","h3_letter_spacing":"0.05em","h4_font_size":"22px","h4_line_height":"1.3","h4_letter_spacing":"0.05em","heading_text_color":"#0b033f","body_text_color":"rgba(11,3,63,0.5)","footer_widgets_bar":"3","footer_widgets_bar_column_1_width":"40%","footer_widgets_bar_column_2_width":"25%","footer_widgets_bar_column_3_width":"35%","footer_bottom_bar_padding":"35px 20px 35px 20px","footer_bottom_bar_bg_color":"#d94d7b","footer_bottom_bar_text_color":"rgba(255,255,255,0.5)","footer_bottom_bar_link_text_color":"rgba(255,255,255,0.5)","footer_bottom_bar_link_hover_text_color":"#ed739b","footer_copyright_content":"Copyright \u00a9 {{year}}. Suki Wordpress Theme","button_padding":"12px 30px 12px 30px","button_border":"0px 0px 0px 0px","button_border_radius":"10px","button_font_weight":"","button_font_size":"","button_bg_color":"#ed739b","button_border_color":"#ed739b","button_hover_border_color":"#d94d7b","button_hover_bg_color":"#d94d7b","link_text_color":"#ed739b","link_hover_text_color":"#d94d7b","footer_widgets_bar_padding":"90px 20px 90px 20px","footer_widgets_bar_bg_color":"#ed739b","footer_widgets_bar_border_color":"#ed739b","footer_widgets_bar_text_color":"rgba(255,255,255,0.8)","footer_widgets_bar_widget_title_decoration":"none","footer_widgets_bar_link_text_color":"rgba(255,255,255,0.8)","footer_widgets_bar_link_hover_text_color":"#ffffff","footer_widgets_bar_widget_title_text_color":"#ffffff","footer_widgets_bar_columns_gutter":"40px","social_facebook":"#","social_instagram":"#","social_linkedin":"#","social_twitter":"#","footer_widgets_bar_widget_title_font_size":"30px","header_elements_main_right":["menu-1","button-1"],"header_button_1_url":"https:\/\/demo.sukiwp.com\/donutime-elementor\/contact\/","header_button_1_text":"Contact","header_main_bar_text_color":"rgba(11,3,63,0.5)","header_main_bar_link_text_color":"rgba(11,3,63,0.5)","input_padding":"16px 30px 16px 30px","input_border_radius":"15px","header_mobile_main_bar_height":"80px","custom_logo_mobile":"[[post_id?post_type=attachment&slug=logo-navy]]","header_mobile_logo_width":"140px","header_transparent":0,"footer_widgets_bar_column_1_width__tablet":"50%","footer_widgets_bar_column_2_width__tablet":"50%","footer_widgets_bar_column_3_width__tablet":"100%","footer_widgets_bar_column_1_width__mobile":"100%","footer_widgets_bar_column_2_width__mobile":"100%","footer_widgets_bar_column_3_width__mobile":"100%","content_layout":"wide","blog_index_grid_columns":"3","entry_grid_header":["header-meta","title"],"entry_grid_header_meta":"{{categories}}","entry_grid_footer":[],"entry_grid_footer_meta":"","blog_featured_posts":1,"blog_featured_posts_layout":"grid-3","blog_featured_posts_items_gutter":"15px","entry_header_meta":"{{categories}}","entry_footer":[],"entry_footer_meta":"","header_mobile_vertical_bar_position":"right","header_mobile_elements_vertical_top":["search-bar","mobile-menu","button-1"],"header_mobile_vertical_bar_alignment":"center","entry_thumbnail_ignore_padding":"0","header_mobile_vertical_bar_full_screen_position":"right","post_single_content_layout":"","error_404_content_header_alignment":"left","e-landing-page_archive_content_header_alignment":"left","e-landing-page_single_content_header_alignment":"left","product_archive_content_header":["breadcrumb","title","archive-description"],"product_single_content_header":["breadcrumb"],"hero":0}